[
    {
        "nome": "A1",
        "alchoholic": "Alcoholic"
    },
    {
        "nome": "ABC",
        "alchoholic": "Alcoholic"
    },
    {
        "nome": "Abilene",
        "alchoholic": "Alcoholic"
    },
    {
        "nome": "Acapulco",
        "alchoholic": "Alcoholic"
    },
    {
        "nome": "Ace",
        "alchoholic": "Alcoholic"
    },
    {
        "nome": "ACID",
        "alchoholic": "Alcoholic"
    },
    {
        "nome": "Adam",
        "alchoholic": "Alcoholic"
    },
    {
        "nome": "Addison",
        "alchoholic": "Alcoholic"
    },
    {
        "nome": "Affair",
        "alchoholic": "Alcoholic"
    },
    {
        "nome": "Affinity",
        "alchoholic": "Alcoholic"
    },
    {
        "nome": "Afterglow",
        "alchoholic": "Non alcoholic"
    },
    {
        "nome": "Afternoon",
        "alchoholic": "Alcoholic"
    },
    {
        "nome": "After sex",
        "alchoholic": "Alcoholic"
    },
    {
        "nome": "A. J.",
        "alchoholic": "Alcoholic"
    },
    {
        "nome": "Alexander",
        "alchoholic": "Alcoholic"
    },
    {
        "nome": "Algonquin",
        "alchoholic": "Alcoholic"
    },
    {
        "nome": "Allegheny",
        "alchoholic": "Alcoholic"
    },
    {
        "nome": "Almeria",
        "alchoholic": "Alcoholic"
    },
    {
        "nome": "Apello",
        "alchoholic": "Non alcoholic"
    },
    {
        "nome": "Applecar",
        "alchoholic": "Alcoholic"
    },
    {
        "nome": "Artillery",
        "alchoholic": "Alcoholic"
    },
    {
        "nome": "AT&T",
        "alchoholic": "Alcoholic"
    },
    {
        "nome": "Autodaf\u00e9",
        "alchoholic": "Alcoholic"
    },
    {
        "nome": "Avalon",
        "alchoholic": "Alcoholic"
    },
    {
        "nome": "Aviation",
        "alchoholic": "Alcoholic"
    },
    {
        "nome": "B-52",
        "alchoholic": "Alcoholic"
    },
    {
        "nome": "B-53",
        "alchoholic": "Alcoholic"
    },
    {
        "nome": "Balmoral",
        "alchoholic": "Alcoholic"
    },
    {
        "nome": "Barracuda",
        "alchoholic": "Alcoholic"
    },
    {
        "nome": "Bellini",
        "alchoholic": "Alcoholic"
    },
    {
        "nome": "Bible Belt",
        "alchoholic": "Alcoholic"
    },
    {
        "nome": "Big Red",
        "alchoholic": "Alcoholic"
    },
    {
        "nome": "Bijou",
        "alchoholic": "Alcoholic"
    },
    {
        "nome": "Blackthorn",
        "alchoholic": "Alcoholic"
    },
    {
        "nome": "Bloody Mary",
        "alchoholic": "Alcoholic"
    },
    {
        "nome": "Bluebird",
        "alchoholic": "Alcoholic"
    },
    {
        "nome": "Blue Lagoon",
        "alchoholic": "Alcoholic"
    },
    {
        "nome": "Bob Marley",
        "alchoholic": "Alcoholic"
    },
    {
        "nome": "Boomerang",
        "alchoholic": "Alcoholic"
    },
    {
        "nome": "Bora Bora",
        "alchoholic": "Non alcoholic"
    },
    {
        "nome": "Boston Sour",
        "alchoholic": "Alcoholic"
    },
    {
        "nome": "Boxcar",
        "alchoholic": "Alcoholic"
    },
    {
        "nome": "Brain Fart",
        "alchoholic": "Alcoholic"
    },
    {
        "nome": "Bramble",
        "alchoholic": "Alcoholic"
    },
    {
        "nome": "Brigadier",
        "alchoholic": "Alcoholic"
    },
    {
        "nome": "Broadside",
        "alchoholic": "Alcoholic"
    },
    {
        "nome": "Brooklyn Cocktail",
        "alchoholic": "Alcoholic"
    },
    {
        "nome": "Bubble Gum",
        "alchoholic": "Alcoholic"
    },
    {
        "nome": "Buccaneer",
        "alchoholic": "Alcoholic"
    },
    {
        "nome": "Bumble Bee",
        "alchoholic": "Alcoholic"
    },
    {
        "nome": "Cafe Savoy",
        "alchoholic": "Alcoholic"
    },
    {
        "nome": "Caipirinha",
        "alchoholic": "Alcoholic"
    },
    {
        "nome": "Caipirissima",
        "alchoholic": "Alcoholic"
    },
    {
        "nome": "Campari Beer",
        "alchoholic": "Alcoholic"
    },
    {
        "nome": "Casa Blanca",
        "alchoholic": "Alcoholic"
    },
    {
        "nome": "Casino",
        "alchoholic": "Alcoholic"
    },
    {
        "nome": "Casino Royale",
        "alchoholic": "Alcoholic"
    },
    {
        "nome": "Cherry Rum",
        "alchoholic": "Alcoholic"
    },
    {
        "nome": "Chicago Fizz",
        "alchoholic": "Alcoholic"
    },
    {
        "nome": "Chocolate Drink",
        "alchoholic": "Non alcoholic"
    },
    {
        "nome": "Chocolate Milk",
        "alchoholic": "Alcoholic"
    },
    {
        "nome": "Citrus Coke",
        "alchoholic": "Alcoholic"
    },
    {
        "nome": "City Slicker",
        "alchoholic": "Alcoholic"
    },
    {
        "nome": "Clove Cocktail",
        "alchoholic": "Alcoholic"
    },
    {
        "nome": "Clover Club",
        "alchoholic": "Alcoholic"
    },
    {
        "nome": "Coffee-Vodka",
        "alchoholic": "Alcoholic"
    },
    {
        "nome": "Coffee Liqueur Cocktail",
        "alchoholic": "Alcoholic"
    },
    {
        "nome": "Coke and Drops",
        "alchoholic": "Non alcoholic"
    },
    {
        "nome": "Corn n Oil",
        "alchoholic": "Alcoholic"
    },
    {
        "nome": "Corpse Reviver",
        "alchoholic": "Alcoholic"
    },
    {
        "nome": "Cosmopolitan",
        "alchoholic": "Alcoholic"
    },
    {
        "nome": "Cream Soda",
        "alchoholic": "Alcoholic"
    },
    {
        "nome": "Creme de Menthe",
        "alchoholic": "Alcoholic"
    },
    {
        "nome": "Cuba Libra",
        "alchoholic": "Alcoholic"
    },
    {
        "nome": "Cuba Libre",
        "alchoholic": "Alcoholic"
    },
    {
        "nome": "Daiquiri",
        "alchoholic": "Alcoholic"
    },
    {
        "nome": "Damned if you do",
        "alchoholic": "Alcoholic"
    },
    {
        "nome": "Danbooka",
        "alchoholic": "Alcoholic"
    },
    {
        "nome": "Dark and Stormy",
        "alchoholic": "Alcoholic"
    },
    {
        "nome": "Dark Caipirinha",
        "alchoholic": "Alcoholic"
    },
    {
        "nome": "Darkwood Sling",
        "alchoholic": "Alcoholic"
    },
    {
        "nome": "Death in the Afternoon",
        "alchoholic": "Alcoholic"
    },
    {
        "nome": "Derby",
        "alchoholic": "Alcoholic"
    },
    {
        "nome": "Diesel",
        "alchoholic": "Alcoholic"
    },
    {
        "nome": "Dirty Martini",
        "alchoholic": "Alcoholic"
    },
    {
        "nome": "Dirty Nipple",
        "alchoholic": "Alcoholic"
    },
    {
        "nome": "Downshift",
        "alchoholic": "Alcoholic"
    },
    {
        "nome": "Dragonfly",
        "alchoholic": "Alcoholic"
    },
    {
        "nome": "Drinking Chocolate",
        "alchoholic": "Non alcoholic"
    },
    {
        "nome": "Dry Martini",
        "alchoholic": "Alcoholic"
    },
    {
        "nome": "Dry Rob Roy",
        "alchoholic": "Alcoholic"
    },
    {
        "nome": "Dubonnet Cocktail",
        "alchoholic": "Alcoholic"
    },
    {
        "nome": "Duchamp's Punch",
        "alchoholic": "Alcoholic"
    },
    {
        "nome": "Egg-Nog - Classic Cooked",
        "alchoholic": "Optional alcohol"
    },
    {
        "nome": "Egg Cream",
        "alchoholic": "Non alcoholic"
    },
    {
        "nome": "Egg Nog #4",
        "alchoholic": "Optional alcohol"
    },
    {
        "nome": "Egg Nog - Healthy",
        "alchoholic": "Optional alcohol"
    },
    {
        "nome": "Elderflower Caipirinha",
        "alchoholic": "Alcoholic"
    },
    {
        "nome": "Empell\u00f3n Cocina's Fat-Washed Mezcal",
        "alchoholic": "Alcoholic"
    },
    {
        "nome": "English Highball",
        "alchoholic": "Alcoholic"
    },
    {
        "nome": "English Rose Cocktail",
        "alchoholic": "Alcoholic"
    },
    {
        "nome": "Espresso Martini",
        "alchoholic": "Alcoholic"
    },
    {
        "nome": "Espresso Rumtini",
        "alchoholic": "Alcoholic"
    },
    {
        "nome": "Fahrenheit 5000",
        "alchoholic": "Alcoholic"
    },
    {
        "nome": "Figgy Thyme",
        "alchoholic": "Alcoholic"
    },
    {
        "nome": "Flaming Dr. Pepper",
        "alchoholic": "Alcoholic"
    },
    {
        "nome": "Flaming Lamborghini",
        "alchoholic": "Alcoholic"
    },
    {
        "nome": "Flander's Flake-Out",
        "alchoholic": "Alcoholic"
    },
    {
        "nome": "Flying Dutchman",
        "alchoholic": "Alcoholic"
    },
    {
        "nome": "Flying Scotchman",
        "alchoholic": "Alcoholic"
    },
    {
        "nome": "Foxy Lady",
        "alchoholic": "Alcoholic"
    },
    {
        "nome": "Frapp\u00e9",
        "alchoholic": "Non alcoholic"
    },
    {
        "nome": "Freddy Kruger",
        "alchoholic": "Alcoholic"
    },
    {
        "nome": "French 75",
        "alchoholic": "Alcoholic"
    },
    {
        "nome": "French Connection",
        "alchoholic": "Alcoholic"
    },
    {
        "nome": "French Martini",
        "alchoholic": "Alcoholic"
    },
    {
        "nome": "French Negroni",
        "alchoholic": "Alcoholic"
    },
    {
        "nome": "Frisco Sour",
        "alchoholic": "Alcoholic"
    },
    {
        "nome": "Fros\u00e9",
        "alchoholic": "Alcoholic"
    },
    {
        "nome": "Frozen Daiquiri",
        "alchoholic": "Alcoholic"
    },
    {
        "nome": "Frozen Mint Daiquiri",
        "alchoholic": "Alcoholic"
    },
    {
        "nome": "Frozen Pineapple Daiquiri",
        "alchoholic": "Alcoholic"
    },
    {
        "nome": "Fruit Cooler",
        "alchoholic": "Non alcoholic"
    },
    {
        "nome": "Fruit Flip-Flop",
        "alchoholic": "Non alcoholic"
    },
    {
        "nome": "Fruit Shake",
        "alchoholic": "Non alcoholic"
    },
    {
        "nome": "Funk and Soul",
        "alchoholic": "Alcoholic"
    },
    {
        "nome": "Fuzzy Asshole",
        "alchoholic": "Alcoholic"
    },
    {
        "nome": "Gagliardo",
        "alchoholic": "Alcoholic"
    },
    {
        "nome": "GG",
        "alchoholic": "Optional alcohol"
    },
    {
        "nome": "Gimlet",
        "alchoholic": "Alcoholic"
    },
    {
        "nome": "Gin Cooler",
        "alchoholic": "Alcoholic"
    },
    {
        "nome": "Gin Daisy",
        "alchoholic": "Alcoholic"
    },
    {
        "nome": "Gin Fizz",
        "alchoholic": "Alcoholic"
    },
    {
        "nome": "Gin Rickey",
        "alchoholic": "Alcoholic"
    },
    {
        "nome": "Gin Sling",
        "alchoholic": "Alcoholic"
    },
    {
        "nome": "Gin Smash",
        "alchoholic": "Alcoholic"
    },
    {
        "nome": "Gin Sour",
        "alchoholic": "Alcoholic"
    },
    {
        "nome": "Gin Squirt",
        "alchoholic": "Alcoholic"
    },
    {
        "nome": "Gin Swizzle",
        "alchoholic": "Alcoholic"
    },
    {
        "nome": "Gin Toddy",
        "alchoholic": "Alcoholic"
    },
    {
        "nome": "Gluehwein",
        "alchoholic": "Optional alcohol"
    },
    {
        "nome": "Godchild",
        "alchoholic": "Alcoholic"
    },
    {
        "nome": "Godfather",
        "alchoholic": "Alcoholic"
    },
    {
        "nome": "Godmother",
        "alchoholic": "Alcoholic"
    },
    {
        "nome": "Golden dream",
        "alchoholic": "Alcoholic"
    },
    {
        "nome": "Grand Blue",
        "alchoholic": "Alcoholic"
    },
    {
        "nome": "Grasshopper",
        "alchoholic": "Alcoholic"
    },
    {
        "nome": "Grass Skirt",
        "alchoholic": "Alcoholic"
    },
    {
        "nome": "Green Goblin",
        "alchoholic": "Alcoholic"
    },
    {
        "nome": "Greyhound",
        "alchoholic": "Alcoholic"
    },
    {
        "nome": "Grim Reaper",
        "alchoholic": "Alcoholic"
    },
    {
        "nome": "Grizzly Bear",
        "alchoholic": "Alcoholic"
    },
    {
        "nome": "Halloween Punch",
        "alchoholic": "Alcoholic"
    },
    {
        "nome": "Happy Skipper",
        "alchoholic": "Alcoholic"
    },
    {
        "nome": "Harvey Wallbanger",
        "alchoholic": "Alcoholic"
    },
    {
        "nome": "Havana Cocktail",
        "alchoholic": "Alcoholic"
    },
    {
        "nome": "Hawaiian Cocktail",
        "alchoholic": "Alcoholic"
    },
    {
        "nome": "H.D.",
        "alchoholic": "Alcoholic"
    },
    {
        "nome": "Hemingway Special",
        "alchoholic": "Alcoholic"
    },
    {
        "nome": "Herbal flame",
        "alchoholic": "Alcoholic"
    },
    {
        "nome": "Highland Fling Cocktail",
        "alchoholic": "Alcoholic"
    },
    {
        "nome": "Holloween Punch",
        "alchoholic": "Non alcoholic"
    },
    {
        "nome": "Homemade Kahlua",
        "alchoholic": "Alcoholic"
    },
    {
        "nome": "Honey Bee",
        "alchoholic": "Alcoholic"
    },
    {
        "nome": "Horse's Neck",
        "alchoholic": "Alcoholic"
    },
    {
        "nome": "Hot Chocolate to Die for",
        "alchoholic": "Non alcoholic"
    },
    {
        "nome": "Hot Creamy Bush",
        "alchoholic": "Alcoholic"
    },
    {
        "nome": "Hot Toddy",
        "alchoholic": "Alcoholic"
    },
    {
        "nome": "Hunter's Moon",
        "alchoholic": "Alcoholic"
    },
    {
        "nome": "Iced Coffee",
        "alchoholic": "Non alcoholic"
    },
    {
        "nome": "Iced Coffee Fillip",
        "alchoholic": "Alcoholic"
    },
    {
        "nome": "Ice Pick",
        "alchoholic": "Alcoholic"
    },
    {
        "nome": "Imperial Cocktail",
        "alchoholic": "Alcoholic"
    },
    {
        "nome": "Imperial Fizz",
        "alchoholic": "Alcoholic"
    },
    {
        "nome": "Ipamena",
        "alchoholic": "Non alcoholic"
    },
    {
        "nome": "Irish Coffee",
        "alchoholic": "Alcoholic"
    },
    {
        "nome": "Irish Cream Cocktail",
        "alchoholic": "Alcoholic"
    },
    {
        "nome": "Irish Curdling Cow",
        "alchoholic": "Alcoholic"
    },
    {
        "nome": "Irish Russian",
        "alchoholic": "Alcoholic"
    },
    {
        "nome": "Irish Spring",
        "alchoholic": "Alcoholic"
    },
    {
        "nome": "Jackhammer",
        "alchoholic": "Alcoholic"
    },
    {
        "nome": "Jack Rose Cocktail",
        "alchoholic": "Alcoholic"
    },
    {
        "nome": "Jack's Vanilla Coke",
        "alchoholic": "Alcoholic"
    },
    {
        "nome": "Jamaica Kiss",
        "alchoholic": "Alcoholic"
    },
    {
        "nome": "Jamaican Coffee",
        "alchoholic": "Alcoholic"
    },
    {
        "nome": "Jam Donut",
        "alchoholic": "Alcoholic"
    },
    {
        "nome": "Japanese Fizz",
        "alchoholic": "Alcoholic"
    },
    {
        "nome": "Jello shots",
        "alchoholic": "Alcoholic"
    },
    {
        "nome": "Jelly Bean",
        "alchoholic": "Alcoholic"
    },
    {
        "nome": "Jewel Of The Nile",
        "alchoholic": "Alcoholic"
    },
    {
        "nome": "Jitterbug",
        "alchoholic": "Alcoholic"
    },
    {
        "nome": "John Collins",
        "alchoholic": "Alcoholic"
    },
    {
        "nome": "Just a Moonmint",
        "alchoholic": "Non alcoholic"
    },
    {
        "nome": "Kamikaze",
        "alchoholic": "Alcoholic"
    },
    {
        "nome": "Karsk",
        "alchoholic": "Alcoholic"
    },
    {
        "nome": "Kentucky B And B",
        "alchoholic": "Alcoholic"
    },
    {
        "nome": "Kentucky Colonel",
        "alchoholic": "Alcoholic"
    },
    {
        "nome": "Kill the cold Smoothie",
        "alchoholic": "Non alcoholic"
    },
    {
        "nome": "Kioki Coffee",
        "alchoholic": "Alcoholic"
    },
    {
        "nome": "Kir",
        "alchoholic": "Alcoholic"
    },
    {
        "nome": "Kir Royale",
        "alchoholic": "Alcoholic"
    },
    {
        "nome": "Kiss me Quick",
        "alchoholic": "Alcoholic"
    },
    {
        "nome": "Kiwi Lemon",
        "alchoholic": "Alcoholic"
    },
    {
        "nome": "Kiwi Papaya Smoothie",
        "alchoholic": "Non alcoholic"
    },
    {
        "nome": "Kool-Aid Shot",
        "alchoholic": "Alcoholic"
    },
    {
        "nome": "Kool-Aid Slammer",
        "alchoholic": "Alcoholic"
    },
    {
        "nome": "Kool First Aid",
        "alchoholic": "Alcoholic"
    },
    {
        "nome": "Kurant Tea",
        "alchoholic": "Alcoholic"
    },
    {
        "nome": "Lady Love Fizz",
        "alchoholic": "Alcoholic"
    },
    {
        "nome": "Lassi - A South Indian Drink",
        "alchoholic": "Non alcoholic"
    },
    {
        "nome": "Lassi - Mango",
        "alchoholic": "Non alcoholic"
    },
    {
        "nome": "Lassi - Sweet",
        "alchoholic": "Non alcoholic"
    },
    {
        "nome": "Lassi Khara",
        "alchoholic": "Non alcoholic"
    },
    {
        "nome": "Lassi Raita",
        "alchoholic": "Non alcoholic"
    },
    {
        "nome": "Lazy Coconut Paloma",
        "alchoholic": "Alcoholic"
    },
    {
        "nome": "Lemon Drop",
        "alchoholic": "Alcoholic"
    },
    {
        "nome": "Lemon Shot",
        "alchoholic": "Alcoholic"
    },
    {
        "nome": "Lemouroudji",
        "alchoholic": "Non alcoholic"
    },
    {
        "nome": "Limeade Cocktail",
        "alchoholic": "Non alcoholic"
    },
    {
        "nome": "Limona Corona",
        "alchoholic": "Alcoholic"
    },
    {
        "nome": "Loch Lomond",
        "alchoholic": "Alcoholic"
    },
    {
        "nome": "London Town",
        "alchoholic": "Alcoholic"
    },
    {
        "nome": "Lone Tree Cocktail",
        "alchoholic": "Alcoholic"
    },
    {
        "nome": "Lone Tree Cooler",
        "alchoholic": "Alcoholic"
    },
    {
        "nome": "Long Island Iced Tea",
        "alchoholic": "Alcoholic"
    },
    {
        "nome": "Long Island Tea",
        "alchoholic": "Alcoholic"
    },
    {
        "nome": "Long vodka",
        "alchoholic": "Alcoholic"
    },
    {
        "nome": "Lord And Lady",
        "alchoholic": "Alcoholic"
    },
    {
        "nome": "Lunch Box",
        "alchoholic": "Alcoholic"
    },
    {
        "nome": "Mai Tai",
        "alchoholic": "Alcoholic"
    },
    {
        "nome": "Manhattan",
        "alchoholic": "Alcoholic"
    },
    {
        "nome": "Margarita",
        "alchoholic": "Alcoholic"
    },
    {
        "nome": "Martinez 2",
        "alchoholic": "Alcoholic"
    },
    {
        "nome": "Martini",
        "alchoholic": "Alcoholic"
    },
    {
        "nome": "Mary Pickford",
        "alchoholic": "Alcoholic"
    },
    {
        "nome": "Masala Chai",
        "alchoholic": "Non alcoholic"
    },
    {
        "nome": "Melya",
        "alchoholic": "Non alcoholic"
    },
    {
        "nome": "Miami Vice",
        "alchoholic": "Alcoholic"
    },
    {
        "nome": "Michelada",
        "alchoholic": "Alcoholic"
    },
    {
        "nome": "Midnight Manx",
        "alchoholic": "Alcoholic"
    },
    {
        "nome": "Midnight Mint",
        "alchoholic": "Alcoholic"
    },
    {
        "nome": "Mimosa",
        "alchoholic": "Alcoholic"
    },
    {
        "nome": "Mint Julep",
        "alchoholic": "Alcoholic"
    },
    {
        "nome": "Mocha-Berry",
        "alchoholic": "Alcoholic"
    },
    {
        "nome": "Mojito",
        "alchoholic": "Alcoholic"
    },
    {
        "nome": "Mojito Extra",
        "alchoholic": "Alcoholic"
    },
    {
        "nome": "Monkey Gland",
        "alchoholic": "Alcoholic"
    },
    {
        "nome": "Monkey Wrench",
        "alchoholic": "Alcoholic"
    },
    {
        "nome": "Moranguito",
        "alchoholic": "Alcoholic"
    },
    {
        "nome": "Moscow Mule",
        "alchoholic": "Alcoholic"
    },
    {
        "nome": "Mother's Milk",
        "alchoholic": "Alcoholic"
    },
    {
        "nome": "Mudslinger",
        "alchoholic": "Alcoholic"
    },
    {
        "nome": "Mulled Wine",
        "alchoholic": "Alcoholic"
    },
    {
        "nome": "Munich Mule",
        "alchoholic": "Alcoholic"
    },
    {
        "nome": "National Aquarium",
        "alchoholic": "Alcoholic"
    },
    {
        "nome": "Negroni",
        "alchoholic": "Alcoholic"
    },
    {
        "nome": "New York Lemonade",
        "alchoholic": "Alcoholic"
    },
    {
        "nome": "New York Sour",
        "alchoholic": "Alcoholic"
    },
    {
        "nome": "Nuked Hot Chocolate",
        "alchoholic": "Non alcoholic"
    },
    {
        "nome": "Nutty Irishman",
        "alchoholic": "Alcoholic"
    },
    {
        "nome": "Oatmeal Cookie",
        "alchoholic": "Alcoholic"
    },
    {
        "nome": "Old Fashioned",
        "alchoholic": "Alcoholic"
    },
    {
        "nome": "Old Pal",
        "alchoholic": "Alcoholic"
    },
    {
        "nome": "Orangeade",
        "alchoholic": "Non alcoholic"
    },
    {
        "nome": "Orange Crush",
        "alchoholic": "Alcoholic"
    },
    {
        "nome": "Orange Oasis",
        "alchoholic": "Alcoholic"
    },
    {
        "nome": "Orange Push-up",
        "alchoholic": "Alcoholic"
    },
    {
        "nome": "Orange Rosemary Collins",
        "alchoholic": "Alcoholic"
    },
    {
        "nome": "Orange Scented Hot Chocolate",
        "alchoholic": "Non alcoholic"
    },
    {
        "nome": "Orange Whip",
        "alchoholic": "Alcoholic"
    },
    {
        "nome": "Oreo Mudslide",
        "alchoholic": "Alcoholic"
    },
    {
        "nome": "Orgasm",
        "alchoholic": "Alcoholic"
    },
    {
        "nome": "Owen's Grandmother's Revenge",
        "alchoholic": "Alcoholic"
    },
    {
        "nome": "Paloma",
        "alchoholic": "Alcoholic"
    },
    {
        "nome": "Paradise",
        "alchoholic": "Alcoholic"
    },
    {
        "nome": "Passion Fruit Martini",
        "alchoholic": "Alcoholic"
    },
    {
        "nome": "Pegu Club",
        "alchoholic": "Alcoholic"
    },
    {
        "nome": "Penicillin",
        "alchoholic": "Alcoholic"
    },
    {
        "nome": "Pina Colada",
        "alchoholic": "Alcoholic"
    },
    {
        "nome": "Pineapple Gingerale Smoothie",
        "alchoholic": "Non alcoholic"
    },
    {
        "nome": "Pineapple Paloma",
        "alchoholic": "Alcoholic"
    },
    {
        "nome": "Pink Gin",
        "alchoholic": "Alcoholic"
    },
    {
        "nome": "Pink Lady",
        "alchoholic": "Alcoholic"
    },
    {
        "nome": "Pink Moon",
        "alchoholic": "Alcoholic"
    },
    {
        "nome": "Pink Panty Pulldowns",
        "alchoholic": "Alcoholic"
    },
    {
        "nome": "Pink Penocha",
        "alchoholic": "Alcoholic"
    },
    {
        "nome": "Pisco Sour",
        "alchoholic": "Alcoholic"
    },
    {
        "nome": "Planter's Punch",
        "alchoholic": "Alcoholic"
    },
    {
        "nome": "Popped cherry",
        "alchoholic": "Alcoholic"
    },
    {
        "nome": "Poppy Cocktail",
        "alchoholic": "Alcoholic"
    },
    {
        "nome": "Port And Starboard",
        "alchoholic": "Alcoholic"
    },
    {
        "nome": "Porto flip",
        "alchoholic": "Alcoholic"
    },
    {
        "nome": "Port Wine Cocktail",
        "alchoholic": "Alcoholic"
    },
    {
        "nome": "Port Wine Flip",
        "alchoholic": "Alcoholic"
    },
    {
        "nome": "Pure Passion",
        "alchoholic": "Alcoholic"
    },
    {
        "nome": "Pysch Vitamin Light",
        "alchoholic": "Non alcoholic"
    },
    {
        "nome": "Quaker's Cocktail",
        "alchoholic": "Alcoholic"
    },
    {
        "nome": "Quarter Deck Cocktail",
        "alchoholic": "Alcoholic"
    },
    {
        "nome": "Queen Bee",
        "alchoholic": "Alcoholic"
    },
    {
        "nome": "Queen Charlotte",
        "alchoholic": "Alcoholic"
    },
    {
        "nome": "Queen Elizabeth",
        "alchoholic": "Alcoholic"
    },
    {
        "nome": "Quentin",
        "alchoholic": "Alcoholic"
    },
    {
        "nome": "Quick-sand",
        "alchoholic": "Alcoholic"
    },
    {
        "nome": "Quick F**K",
        "alchoholic": "Alcoholic"
    },
    {
        "nome": "Radioactive Long Island Iced Tea",
        "alchoholic": "Alcoholic"
    },
    {
        "nome": "Radler",
        "alchoholic": "Alcoholic"
    },
    {
        "nome": "Rail Splitter",
        "alchoholic": "Non alcoholic"
    },
    {
        "nome": "Raspberry Cooler",
        "alchoholic": "Alcoholic"
    },
    {
        "nome": "Raspberry Julep",
        "alchoholic": "Alcoholic"
    },
    {
        "nome": "Red Snapper",
        "alchoholic": "Alcoholic"
    },
    {
        "nome": "Rose Cocktail",
        "alchoholic": "Alcoholic"
    },
    {
        "nome": "Rosemary Blue",
        "alchoholic": "Alcoholic"
    },
    {
        "nome": "Royal Bitch",
        "alchoholic": "Alcoholic"
    },
    {
        "nome": "Royal Fizz",
        "alchoholic": "Alcoholic"
    },
    {
        "nome": "Royal Flush",
        "alchoholic": "Alcoholic"
    },
    {
        "nome": "Royal Gin Fizz",
        "alchoholic": "Alcoholic"
    },
    {
        "nome": "Ruby Tuesday",
        "alchoholic": "Alcoholic"
    },
    {
        "nome": "Rum Cobbler",
        "alchoholic": "Alcoholic"
    },
    {
        "nome": "Rum Cooler",
        "alchoholic": "Alcoholic"
    },
    {
        "nome": "Rum Milk Punch",
        "alchoholic": "Alcoholic"
    },
    {
        "nome": "Rum Old-fashioned",
        "alchoholic": "Alcoholic"
    },
    {
        "nome": "Rum Punch",
        "alchoholic": "Alcoholic"
    },
    {
        "nome": "Rum Runner",
        "alchoholic": "Alcoholic"
    },
    {
        "nome": "Rum Screwdriver",
        "alchoholic": "Alcoholic"
    },
    {
        "nome": "Rum Sour",
        "alchoholic": "Alcoholic"
    },
    {
        "nome": "Rum Toddy",
        "alchoholic": "Alcoholic"
    },
    {
        "nome": "Russian Spring Punch",
        "alchoholic": "Alcoholic"
    },
    {
        "nome": "Rusty Nail",
        "alchoholic": "Alcoholic"
    },
    {
        "nome": "Salty Dog",
        "alchoholic": "Alcoholic"
    },
    {
        "nome": "San Francisco Cocktail",
        "alchoholic": "Alcoholic"
    },
    {
        "nome": "Sangria",
        "alchoholic": "Alcoholic"
    },
    {
        "nome": "Sazerac",
        "alchoholic": "Alcoholic"
    },
    {
        "nome": "Scooter",
        "alchoholic": "Alcoholic"
    },
    {
        "nome": "Scotch Sour",
        "alchoholic": "Alcoholic"
    },
    {
        "nome": "Screwdriver",
        "alchoholic": "Alcoholic"
    },
    {
        "nome": "Sea breeze",
        "alchoholic": "Alcoholic"
    },
    {
        "nome": "Shark Attack",
        "alchoholic": "Alcoholic"
    },
    {
        "nome": "Sherry Eggnog",
        "alchoholic": "Alcoholic"
    },
    {
        "nome": "Sherry Flip",
        "alchoholic": "Alcoholic"
    },
    {
        "nome": "Shot-gun",
        "alchoholic": "Alcoholic"
    },
    {
        "nome": "Sidecar",
        "alchoholic": "Alcoholic"
    },
    {
        "nome": "Smut",
        "alchoholic": "Alcoholic"
    },
    {
        "nome": "Snowball",
        "alchoholic": "Alcoholic"
    },
    {
        "nome": "Snowday",
        "alchoholic": "Alcoholic"
    },
    {
        "nome": "Sol Y Sombra",
        "alchoholic": "Alcoholic"
    },
    {
        "nome": "Space Odyssey",
        "alchoholic": "Alcoholic"
    },
    {
        "nome": "Spice 75",
        "alchoholic": "Alcoholic"
    },
    {
        "nome": "Spritz",
        "alchoholic": "Alcoholic"
    },
    {
        "nome": "Stinger",
        "alchoholic": "Alcoholic"
    },
    {
        "nome": "Stone Sour",
        "alchoholic": "Alcoholic"
    },
    {
        "nome": "Sweet Bananas",
        "alchoholic": "Non alcoholic"
    },
    {
        "nome": "Sweet Sangria",
        "alchoholic": "Alcoholic"
    },
    {
        "nome": "Sweet Tooth",
        "alchoholic": "Alcoholic"
    },
    {
        "nome": "Talos Coffee",
        "alchoholic": "Alcoholic"
    },
    {
        "nome": "Tennesee Mud",
        "alchoholic": "Alcoholic"
    },
    {
        "nome": "Tequila Fizz",
        "alchoholic": "Alcoholic"
    },
    {
        "nome": "Tequila Slammer",
        "alchoholic": "Alcoholic"
    },
    {
        "nome": "Tequila Sour",
        "alchoholic": "Alcoholic"
    },
    {
        "nome": "Tequila Sunrise",
        "alchoholic": "Alcoholic"
    },
    {
        "nome": "Tequila Surprise",
        "alchoholic": "Alcoholic"
    },
    {
        "nome": "Texas Rattlesnake",
        "alchoholic": "Alcoholic"
    },
    {
        "nome": "Texas Sling",
        "alchoholic": "Alcoholic"
    },
    {
        "nome": "Thai Coffee",
        "alchoholic": "Non alcoholic"
    },
    {
        "nome": "Thai Iced Coffee",
        "alchoholic": "Non alcoholic"
    },
    {
        "nome": "Thai Iced Tea",
        "alchoholic": "Non alcoholic"
    },
    {
        "nome": "The Galah",
        "alchoholic": "Alcoholic"
    },
    {
        "nome": "The Jimmy Conway",
        "alchoholic": "Alcoholic"
    },
    {
        "nome": "The Last Word",
        "alchoholic": "Alcoholic"
    },
    {
        "nome": "The Laverstoke",
        "alchoholic": "Alcoholic"
    },
    {
        "nome": "The Philosopher",
        "alchoholic": "Alcoholic"
    },
    {
        "nome": "Thriller",
        "alchoholic": "Alcoholic"
    },
    {
        "nome": "Tia-Maria",
        "alchoholic": "Alcoholic"
    },
    {
        "nome": "Tipperary",
        "alchoholic": "Alcoholic"
    },
    {
        "nome": "Tomato Tang",
        "alchoholic": "Non alcoholic"
    },
    {
        "nome": "Tom Collins",
        "alchoholic": "Alcoholic"
    },
    {
        "nome": "Turf Cocktail",
        "alchoholic": "Alcoholic"
    },
    {
        "nome": "Turkeyball",
        "alchoholic": "Alcoholic"
    },
    {
        "nome": "Tuxedo Cocktail",
        "alchoholic": "Alcoholic"
    },
    {
        "nome": "Valencia Cocktail",
        "alchoholic": "Alcoholic"
    },
    {
        "nome": "Vampiro",
        "alchoholic": "Alcoholic"
    },
    {
        "nome": "Van Vleet",
        "alchoholic": "Alcoholic"
    },
    {
        "nome": "Vermouth Cassis",
        "alchoholic": "Alcoholic"
    },
    {
        "nome": "Vesper",
        "alchoholic": "Alcoholic"
    },
    {
        "nome": "Vesuvio",
        "alchoholic": "Alcoholic"
    },
    {
        "nome": "Veteran",
        "alchoholic": "Alcoholic"
    },
    {
        "nome": "Victor",
        "alchoholic": "Alcoholic"
    },
    {
        "nome": "Victory Collins",
        "alchoholic": "Alcoholic"
    },
    {
        "nome": "Vodka And Tonic",
        "alchoholic": "Alcoholic"
    },
    {
        "nome": "Vodka Fizz",
        "alchoholic": "Alcoholic"
    },
    {
        "nome": "Vodka Martini",
        "alchoholic": "Alcoholic"
    },
    {
        "nome": "Vodka Russian",
        "alchoholic": "Alcoholic"
    },
    {
        "nome": "Waikiki Beachcomber",
        "alchoholic": "Alcoholic"
    },
    {
        "nome": "Whiskey Sour",
        "alchoholic": "Alcoholic"
    },
    {
        "nome": "Whisky Mac",
        "alchoholic": "Alcoholic"
    },
    {
        "nome": "Whitecap Margarita",
        "alchoholic": "Alcoholic"
    },
    {
        "nome": "White Lady",
        "alchoholic": "Alcoholic"
    },
    {
        "nome": "White Russian",
        "alchoholic": "Alcoholic"
    },
    {
        "nome": "White Wine Sangria",
        "alchoholic": "Alcoholic"
    },
    {
        "nome": "Wine Cooler",
        "alchoholic": "Optional alcohol"
    },
    {
        "nome": "Wine Punch",
        "alchoholic": "Alcoholic"
    },
    {
        "nome": "Winter Paloma",
        "alchoholic": "Alcoholic"
    },
    {
        "nome": "Winter Rita",
        "alchoholic": "Alcoholic"
    },
    {
        "nome": "Yellow Bird",
        "alchoholic": "Alcoholic"
    },
    {
        "nome": "Yoghurt Cooler",
        "alchoholic": "Non alcoholic"
    },
    {
        "nome": "Zambeer",
        "alchoholic": "Alcoholic"
    },
    {
        "nome": "Zenmeister",
        "alchoholic": "Alcoholic"
    },
    {
        "nome": "Ziemes Martini Apfelsaft",
        "alchoholic": "Alcoholic"
    },
    {
        "nome": "Zima Blaster",
        "alchoholic": "Alcoholic"
    },
    {
        "nome": "Zimadori Zinger",
        "alchoholic": "Alcoholic"
    },
    {
        "nome": "Zinger",
        "alchoholic": "Alcoholic"
    },
    {
        "nome": "Zipperhead",
        "alchoholic": "Alcoholic"
    },
    {
        "nome": "Zippy's Revenge",
        "alchoholic": "Alcoholic"
    },
    {
        "nome": "Zizi Coin-coin",
        "alchoholic": "Alcoholic"
    },
    {
        "nome": "Zoksel",
        "alchoholic": "Alcoholic"
    },
    {
        "nome": "Zombie",
        "alchoholic": "Alcoholic"
    },
    {
        "nome": "Zorbatini",
        "alchoholic": "Alcoholic"
    },
    {
        "nome": "Zorro",
        "alchoholic": "Alcoholic"
    },
    {
        "nome": "1-900-FUK-MEUP",
        "alchoholic": "Alcoholic"
    },
    {
        "nome": "110 in the shade",
        "alchoholic": "Alcoholic"
    },
    {
        "nome": "151 Florida Bushwacker",
        "alchoholic": "Alcoholic"
    },
    {
        "nome": "155 Belmont",
        "alchoholic": "Alcoholic"
    },
    {
        "nome": "24k nightmare",
        "alchoholic": "Alcoholic"
    },
    {
        "nome": "252",
        "alchoholic": "Alcoholic"
    },
    {
        "nome": "3-Mile Long Island Iced Tea",
        "alchoholic": "Alcoholic"
    },
    {
        "nome": "3 Wise Men",
        "alchoholic": "Alcoholic"
    },
    {
        "nome": "410 Gone",
        "alchoholic": "Alcoholic"
    },
    {
        "nome": "501 Blue",
        "alchoholic": "Alcoholic"
    },
    {
        "nome": "50/50",
        "alchoholic": "Alcoholic"
    },
    {
        "nome": "57 Chevy with a White License Plate",
        "alchoholic": "Alcoholic"
    },
    {
        "nome": "69 Special",
        "alchoholic": "Alcoholic"
    },
    {
        "nome": "747",
        "alchoholic": "Alcoholic"
    },
    {
        "nome": "747 Drink",
        "alchoholic": "Alcoholic"
    },
    {
        "nome": "9 1/2 Weeks",
        "alchoholic": "Alcoholic"
    }
]